langchain_chatglm/__init__.py
langchain_chatglm/llms/__init__.py
langchain_chatglm/llms/chatglm_pipeline.py
langchain_chatglm-0.0.13.dist-info/LICENSE
langchain_chatglm-0.0.13.dist-info/METADATA
langchain_chatglm-0.0.13.dist-info/WHEEL
langchain_chatglm-0.0.13.dist-info/top_level.txt
langchain_chatglm-0.0.13.dist-info/RECORD
