Metadata-Version: 2.1
Name: langchain-chatglm
Version: 0.0.13
Summary: esay use ChatGLM in LangChain.
Author-email: Sim Tsai <13759975+SimTsai@users.noreply.github.com>
Project-URL: Homepage, https://github.com/SimTsai/langchain_chatglm
Project-URL: Bug Tracker, https://github.com/SimTsai/langchain_chatglm/issues
Classifier: Programming Language :: Python :: 3.10
Classifier: License :: OSI Approved :: MIT License
Classifier: Operating System :: OS Independent
Requires-Python: >=3.10
License-File: LICENSE
Requires-Dist: pydantic (<2)
Requires-Dist: langchain
Requires-Dist: transformers
Requires-Dist: torch
